BitFieldArray/__init__.py
BitFieldArray/bit_field_array.py
BitFieldArray-1.0.3.dist-info/METADATA
BitFieldArray-1.0.3.dist-info/WHEEL
BitFieldArray-1.0.3.dist-info/top_level.txt
BitFieldArray-1.0.3.dist-info/RECORD
