Metadata-Version: 2.1
Name: BitFieldArray
Version: 1.0.3
Summary: TA module to convert arrays into bit field array. Usually useful for transmitting arrays and structures over the network.
Home-page: https://github.com/jonatan1609/BitFieldArray
Author: Jonathan
Author-email: pybots.il@gmail.com
License: UNKNOWN
Platform: UNKNOWN
Classifier: License :: OSI Approved :: The Unlicense (Unlicense)
Classifier: Programming Language :: Python :: 3.5
Classifier: Programming Language :: Python :: 3.6
Classifier: Programming Language :: Python :: 3.7
Classifier: Programming Language :: Python :: 3.8
Classifier: Programming Language :: Python :: 3.9
Classifier: Operating System :: OS Independent
Requires-Python: >=3.5
